{
  "moduleCount": 1,
  "crossEdgeRatio": 0,
  "nodeList": [
    {
      "x": 386.0169018300527,
      "y": 89.91094021788703,
      "g": "M"
    },
    {
      "x": 325.71389852794067,
      "y": 204.22259456992705,
      "g": "M"
    },
    {
      "x": 224.9456664489083,
      "y": 291.0580648827472,
      "g": "M"
    },
    {
      "x": 97.68709658908082,
      "y": 341.47475284317005,
      "g": "M"
    },
    {
      "x": -41.06056363632997,
      "y": 343.25560840440494,
      "g": "M"
    },
    {
      "x": -172.24640425851277,
      "y": 294.29725760098796,
      "g": "M"
    },
    {
      "x": -274.7455570674747,
      "y": 198.2767908848929,
      "g": "M"
    },
    {
      "x": -330.8738998450661,
      "y": 69.2324929301236,
      "g": "M"
    },
    {
      "x": -331.30661746888325,
      "y": -71.3646713606194,
      "g": "M"
    },
    {
      "x": -276.5945658222998,
      "y": -200.63178191897356,
      "g": "M"
    },
    {
      "x": -176.650840858671,
      "y": -298.05148932942916,
      "g": "M"
    },
    {
      "x": -48.601001157399274,
      "y": -350.87021957794093,
      "g": "M"
    },
    {
      "x": 87.57022385304599,
      "y": -355.7052651208907,
      "g": "M"
    },
    {
      "x": 214.31305646824447,
      "y": -317.1172179884542,
      "g": "M"
    },
    {
      "x": 315.83260344750653,
      "y": -237.98785595215062,
      "g": "M"
    }
  ],
  "degreeDist": {
    "values": [
      1,
      2,
      2,
      2,
      2,
      2,
      2,
      2,
      2,
      2,
      2,
      2,
      2,
      2,
      1
    ],
    "mean": 1.8666666666666667,
    "max": 2,
    "gini": 0.06190476190476191
  },
  "chainNodePos": [
    [
      {
        "x": 386.0169018300527,
        "y": 89.91094021788703
      },
      {
        "x": 325.71389852794067,
        "y": 204.22259456992705
      },
      {
        "x": 224.9456664489083,
        "y": 291.0580648827472
      },
      {
        "x": 97.68709658908082,
        "y": 341.47475284317005
      },
      {
        "x": -41.06056363632997,
        "y": 343.25560840440494
      },
      {
        "x": -172.24640425851277,
        "y": 294.29725760098796
      },
      {
        "x": -274.7455570674747,
        "y": 198.2767908848929
      },
      {
        "x": -330.8738998450661,
        "y": 69.2324929301236
      },
      {
        "x": -331.30661746888325,
        "y": -71.3646713606194
      },
      {
        "x": -276.5945658222998,
        "y": -200.63178191897356
      },
      {
        "x": -176.650840858671,
        "y": -298.05148932942916
      },
      {
        "x": -48.601001157399274,
        "y": -350.87021957794093
      },
      {
        "x": 87.57022385304599,
        "y": -355.7052651208907
      },
      {
        "x": 214.31305646824447,
        "y": -317.1172179884542
      },
      {
        "x": 315.83260344750653,
        "y": -237.98785595215062
      }
    ]
  ],
  "edgeAngles": [
    117.81306067581475,
    139.24738743413837,
    158.38775788071027,
    179.26463693319877,
    -159.5345042503056,
    -136.86918387805244,
    -113.50682738553644,
    -90.17633936935465,
    -67.05958409905641,
    -44.26730261895455,
    -22.41544823759407,
    -2.033552757156631,
    16.933363802694103,
    37.934615932647326
  ],
  "edgeVisibility": {
    "ratio": 1,
    "avgGap": 124.8292851121582,
    "minGap": 116.7154783044642,
    "invisible": []
  },
  "nodeOverlap": {
    "ratio": 0,
    "maxOverlap": 0,
    "overlapping": []
  },
  "edgeCrossings": {
    "count": 0,
    "ratio": 0,
    "normalised": 0
  },
  "layoutStress": {
    "stress": 7.006202599652491,
    "perEdge": 0.06672573904430944
  },
  "hubCentrality": {
    "hubs": [],
    "avgNormalised": 0
  },
  "chainLinearity": {
    "ratio": 1.0128273970593669,
    "straightness": 1,
    "chains": [
      {
        "ratio": 1.0128273970593669,
        "major": 707.5566468992631,
        "minor": 698.5954852263833,
        "stepAngles": [
          21.43432675832362,
          19.14037044657188,
          20.876879052488537,
          21.200858816495597,
          22.66532037225315,
          23.362356492516007,
          23.330488016181782,
          23.116755270298235,
          22.79228148010186,
          21.851854381360486,
          20.381895480437436,
          18.966916559850734,
          21.00125212995323
        ],
        "straightness": 1
      }
    ]
  },
  "blobIntegrity": {
    "ratio": 1,
    "violations": [],
    "blobRadii": {}
  },
  "blobSeparation": {
    "minClearance": null,
    "avgClearance": null,
    "separationRatio": null,
    "overlapping": []
  },
  "gestaltProximity": {
    "withinAvg": 487.99940621718764,
    "betweenAvg": null,
    "ratio": 0,
    "cohesion": 1
  },
  "angularResolution": {
    "minAngle": 156.637643507484,
    "avgMinAngle": 158.45218805716675,
    "poorNodes": []
  },
  "edgeLengthUniformity": {
    "mean": 136.8292851121582,
    "stddev": 4.108780591946221,
    "cv": 0.030028517569015117,
    "min": 128.7154783044642,
    "max": 140.7224989033313
  },
  "crossModuleEdgeVisibility": {
    "ratio": 1,
    "count": 0,
    "visible": 0
  },
  "nodeSizeVariation": {
    "cv": 0,
    "mean": 6,
    "stddev": 0,
    "min": 6,
    "max": 6
  },
  "prominentNodeVisibility": {
    "ratio": 1,
    "topN": [
      {
        "id": "n0",
        "group": "M",
        "groupPath": [
          "M"
        ],
        "val": 6,
        "x": 386.0169018300527,
        "y": 89.91094021788703,
        "vx": 0.000002027749594580162,
        "vy": 0.0000034767714404596438,
        "index": 0
      },
      {
        "id": "n1",
        "group": "M",
        "groupPath": [
          "M"
        ],
        "val": 6,
        "x": 325.71389852794067,
        "y": 204.22259456992705,
        "vx": 8.233267734023188e-7,
        "vy": 0.000002859196564880685,
        "index": 1
      },
      {
        "id": "n2",
        "group": "M",
        "groupPath": [
          "M"
        ],
        "val": 6,
        "x": 224.9456664489083,
        "y": 291.0580648827472,
        "vx": 5.42071042466319e-8,
        "vy": 0.00000205157293690242,
        "index": 2
      },
      {
        "id": "n3",
        "group": "M",
        "groupPath": [
          "M"
        ],
        "val": 6,
        "x": 97.68709658908082,
        "y": 341.47475284317005,
        "vx": -3.296118822174128e-7,
        "vy": 0.000001357548675872136,
        "index": 3
      },
      {
        "id": "n4",
        "group": "M",
        "groupPath": [
          "M"
        ],
        "val": 6,
        "x": -41.06056363632997,
        "y": 343.25560840440494,
        "vx": -4.602052742185252e-7,
        "vy": 8.485352258371304e-7,
        "index": 4
      }
    ],
    "obscured": []
  },
  "qualityScore": {
    "score": 99.3,
    "components": {
      "edgeVisibility": 1,
      "noOverlap": 1,
      "fewCrossings": 1,
      "lowStress": 0.9666371304778453,
      "gestaltCohesion": 1,
      "blobIntegrity": 1
    },
    "raw": {
      "vis": {
        "ratio": 1,
        "avgGap": 124.8292851121582,
        "minGap": 116.7154783044642,
        "invisible": []
      },
      "ovlp": {
        "ratio": 0,
        "maxOverlap": 0,
        "overlapping": []
      },
      "cross": {
        "count": 0,
        "ratio": 0,
        "normalised": 0
      },
      "stress": {
        "stress": 7.006202599652491,
        "perEdge": 0.06672573904430944
      },
      "prox": {
        "withinAvg": 487.99940621718764,
        "betweenAvg": null,
        "ratio": 0,
        "cohesion": 1
      },
      "integ": {
        "ratio": 1,
        "violations": [],
        "blobRadii": {}
      }
    }
  }
}